{
  "id": "v1/routine-tr",
  "version": "1.0.0",
  "category": "routine",
  "requiredFields": [
    {
      "id": "station_name",
      "label": "Coast station called",
      "patterns": ["RADIO|COAST\\s*GUARDS?|\\bRCC\\b|PORT\\s*CONTROL"],
      "required": true
    },
    {
      "id": "this_is",
      "label": "THIS IS",
      "patterns": ["THIS\\s+IS"],
      "required": true
    },
    {
      "id": "vessel_name",
      "label": "Own vessel name",
      "patterns": ["SEA\\s*SPRITE"],
      "required": true
    },
    {
      "id": "callsign",
      "label": "Callsign or MMSI",
      "patterns": ["\\b\\d{3}[\\s-]*\\d{3}[\\s-]*\\d{3}\\b|MMSI"],
      "required": true
    },
    {
      "id": "tr_keyword",
      "label": "Transit Report keyword (TR)",
      "patterns": ["TRANSIT\\s*REPORT|\\bTR\\b|TANGO\\s*ROMEO"],
      "required": true
    },
    {
      "id": "voyage",
      "label": "Voyage details (from/to, ETA)",
      "patterns": ["BOUND|FROM|TO|ETA|DEPART|DESTINATION"],
      "required": true
    },
    {
      "id": "position",
      "label": "Position",
      "patterns": [
        "\\d+.*(?:NORTH|SOUTH|EAST|WEST|[NS]).*\\d+|(?:POSITION|LATITUDE|LONGITUDE)\\b(?=.*\\d)"
      ],
      "required": true
    },
    {
      "id": "persons",
      "label": "Persons on board",
      "patterns": ["PERSON|PERSONS|POB|CREW|SOULS|ON\\s*BOARD"],
      "required": true
    }
  ],
  "prowordRules": [
    { "id": "this_is", "label": "THIS IS", "pattern": "THIS\\s+IS" },
    { "id": "over", "label": "OVER", "pattern": "\\bOVER\\b" }
  ],
  "sequenceRules": {
    "fieldOrder": [
      "station_name",
      "this_is",
      "vessel_name",
      "callsign",
      "tr_keyword",
      "position",
      "voyage",
      "persons",
      "over"
    ]
  },
  "sequenceParts": [
    {
      "id": "voice_report",
      "label": "Voice Transit Report (working channel)",
      "items": [
        { "id": "addressee", "label": "Coast station name" },
        { "id": "this_is", "label": "THIS IS" },
        { "id": "vessel", "label": "Vessel name" },
        { "id": "callsign", "label": "Callsign / MMSI" },
        { "id": "tr_keyword", "label": "Transit Report (TR)" },
        { "id": "position", "label": "Position" },
        { "id": "tr_voyage", "label": "Voyage details (from/to, ETA)" },
        { "id": "persons", "label": "Persons on board" },
        { "id": "over", "label": "OVER" }
      ]
    }
  ],
  "channelRules": {
    "requiredChannel": 26,
    "blockChannel70Voice": true
  },
  "dscRules": {
    "required": true,
    "beforeFirstVoiceTurn": true
  }
}
